oradump/__init__.py
oradump/main.sqtmpl
oradump/oradump.py
oradump/utils.py
oradump-1.0.7.dist-info/METADATA
oradump-1.0.7.dist-info/WHEEL
oradump-1.0.7.dist-info/top_level.txt
oradump-1.0.7.dist-info/RECORD
