Metadata-Version: 2.1
Name: oradump
Version: 1.0.7
Summary: Just a package for simple extracting data from Oracle database
Home-page: https://github.com/elessarelfstone/oradump
Author: Dauren Sdykov
License: UNKNOWN
Platform: UNKNOWN
